gearman/__init__.py
gearman/admin_client.py
gearman/admin_client_handler.py
gearman/client.py
gearman/client_handler.py
gearman/command_handler.py
gearman/compat.py
gearman/connection.py
gearman/connection_manager.py
gearman/constants.py
gearman/errors.py
gearman/io.py
gearman/job.py
gearman/protocol.py
gearman/util.py
gearman/version.py
gearman/worker.py
gearman/worker_handler.py
pygearman-0.2.3.dist-info/licenses/AUTHORS.txt
pygearman-0.2.3.dist-info/licenses/LICENSE.txt
pygearman-0.2.3.dist-info/METADATA
pygearman-0.2.3.dist-info/WHEEL
pygearman-0.2.3.dist-info/top_level.txt
pygearman-0.2.3.dist-info/RECORD
